pytest_stress/__init__.py
pytest_stress/pytest_stress.py
pytest_stress-1.0.1.dist-info/AUTHORS
pytest_stress-1.0.1.dist-info/LICENSE
pytest_stress-1.0.1.dist-info/METADATA
pytest_stress-1.0.1.dist-info/WHEEL
pytest_stress-1.0.1.dist-info/entry_points.txt
pytest_stress-1.0.1.dist-info/top_level.txt
pytest_stress-1.0.1.dist-info/RECORD
