Metadata-Version: 2.1
Name: pytest-stress
Version: 1.0.1
Summary: A Pytest plugin that allows you to loop tests for a user defined amount of time.
Home-page: https://pypi.org/project/pytest-stress
Author: Imran Mumtaz
Author-email: iomumtaz@gmail.com
Maintainer: Imran Mumtaz
Maintainer-email: iomumtaz@gmail.com
License: MIT
Project-URL: Homepage, https://github.com/ImXron/pytest-stress
Project-URL: Source, https://github.com/ImXron/pytest-stress
Project-URL: Tracker, https://github.com/ImXron/pytest-stress/issues
Platform: UNKNOWN
Classifier: Development Status :: 4 - Beta
Classifier: Framework :: Pytest
Classifier: Intended Audience :: Developers
Classifier: Topic :: Software Development :: Testing
Classifier: Programming Language :: Python
Classifier: Programming Language :: Python :: 3
Classifier: Programming Language :: Python :: 3.5
Classifier: Programming Language :: Python :: 3.6
Classifier: Programming Language :: Python :: 3.7
Classifier: Programming Language :: Python :: 3.8
Classifier: Operating System :: OS Independent
Classifier: License :: OSI Approved :: MIT License
Requires-Python: >=3.5
Requires-Dist: pytest (>=3.6.0)
